cv_iml/__init__.py
cv_iml/iml.py
cv_iml-0.0.2.dist-info/LICENSE
cv_iml-0.0.2.dist-info/METADATA
cv_iml-0.0.2.dist-info/WHEEL
cv_iml-0.0.2.dist-info/top_level.txt
cv_iml-0.0.2.dist-info/RECORD
